examples/__init__.py
pysent3/__init__.py
pysent3/base.py
pysent3/hiv4.py
pysent3/lm.py
pysent3/utils.py
pysent3/static/Currencies.txt
pysent3/static/DatesandNumbers.txt
pysent3/static/Generic.txt
pysent3/static/Geographic.txt
pysent3/static/HIV-4.csv
pysent3/static/LM.csv
pysent3/static/Names.txt
pysent3/static/NegationWords.txt
tests/__init__.py
tests/test_dict.py
tests/test_utils.py
pysent3-0.1.2.dist-info/LICENSE
pysent3-0.1.2.dist-info/METADATA
pysent3-0.1.2.dist-info/WHEEL
pysent3-0.1.2.dist-info/entry_points.txt
pysent3-0.1.2.dist-info/top_level.txt
pysent3-0.1.2.dist-info/RECORD
