Metadata-Version: 2.1
Name: pysent3
Version: 0.1.2
Summary: Sentiment Analysis in Python using a Dictionary Approach
Home-page: https://github.com/franaguila/pysentiment
Author: Fran Aguila
Author-email: francescaaguila@gmail.com
License: MIT
Project-URL: Code, https://github.com/franaguila/pysentiment
Project-URL: Documentation, https://franaguila.github.io/pysentiment
Platform: UNKNOWN
Classifier: Development Status :: 3 - Alpha
Classifier: Intended Audience :: Developers
Classifier: Programming Language :: Python :: 3.6
Classifier: Programming Language :: Python :: 3.7
License-File: LICENSE
Requires-Dist: pandas
Requires-Dist: nltk (>=2.0)
